fiat_toolbox/__init__.py
fiat_toolbox/utils.py
fiat_toolbox/equity/__init__.py
fiat_toolbox/equity/equity.py
fiat_toolbox/equity/fiat_functions.py
fiat_toolbox/infographics/__init__.py
fiat_toolbox/infographics/infographics.py
fiat_toolbox/infographics/infographics_factory.py
fiat_toolbox/infographics/infographics_interface.py
fiat_toolbox/infographics/risk_infographics.py
fiat_toolbox/metrics_writer/__init__.py
fiat_toolbox/metrics_writer/fiat_metrics_interface.py
fiat_toolbox/metrics_writer/fiat_read_metrics_file.py
fiat_toolbox/metrics_writer/fiat_write_metrics_file.py
fiat_toolbox/metrics_writer/fiat_write_return_period_threshold.py
fiat_toolbox/spatial_output/__init__.py
fiat_toolbox/spatial_output/aggregation_areas.py
fiat_toolbox/spatial_output/footprints.py
fiat_toolbox-0.1.22.dist-info/METADATA
fiat_toolbox-0.1.22.dist-info/WHEEL
fiat_toolbox-0.1.22.dist-info/licenses/LICENSE
fiat_toolbox-0.1.22.dist-info/RECORD
