Metadata-Version: 2.4
Name: fiat_toolbox
Version: 0.1.22
Summary: A collection of modules for post-processing Delft-FIAT output.
Project-URL: Source, https://github.com/Deltares/fiat_toolbox
Author-email: Panos Athanasiou <Panos.Athanasiou@deltares.nl>, Luuk Blom <Luuk.Blom@deltares.nl>, Sarah Rautenbach <sarah.rautenbach@deltares.nl>, Daley Adrichem <Daley.Adrichem@deltares.nl>
License: MIT License
License-File: LICENSE
Classifier: Intended Audience :: Science/Research
Classifier: License :: CC0 1.0 Universal (CC0 1.0) Public Domain Dedication
Classifier: Topic :: Scientific/Engineering :: Hydrology
Requires-Python: >=3.10
Requires-Dist: duckdb<1.3,>=1.0
Requires-Dist: geopandas
Requires-Dist: numpy
Requires-Dist: pandas
Requires-Dist: parse
Requires-Dist: pillow
Requires-Dist: plotly
Requires-Dist: pydantic
Requires-Dist: toml
Requires-Dist: tomli
Requires-Dist: validators
Provides-Extra: lint
Requires-Dist: pre-commit; extra == 'lint'
Requires-Dist: ruff; extra == 'lint'
Provides-Extra: test
Requires-Dist: pytest; extra == 'test'
Requires-Dist: pytest-cov; extra == 'test'
